runtime_final/__init__.py
runtime_final/_tests.py
runtime_final-1.2.0.dist-info/LICENSE
runtime_final-1.2.0.dist-info/METADATA
runtime_final-1.2.0.dist-info/WHEEL
runtime_final-1.2.0.dist-info/top_level.txt
runtime_final-1.2.0.dist-info/RECORD
