Metadata-Version: 2.1
Name: runtime-final
Version: 1.2.0
Summary: Declare final Python classes and methods at runtime.
Home-page: https://github.com/nerdguyahmad/runtime-final
Author: nerdguyahmad
License: MIT
Project-URL: Documentation, https://runtime-final.readthedocs.io
Project-URL: Issue tracker, https://github.com/nerdguyahmad/runtime-final/issues
Classifier: Development Status :: 5 - Production/Stable
Classifier: License :: OSI Approved :: MIT License
Classifier: Intended Audience :: Developers
Classifier: Natural Language :: English
Classifier: Operating System :: OS Independent
Classifier: Programming Language :: Python :: 3.6
Classifier: Programming Language :: Python :: 3.7
Classifier: Programming Language :: Python :: 3.8
Classifier: Programming Language :: Python :: 3.9
Classifier: Programming Language :: Python :: 3.10
Classifier: Topic :: Internet
Classifier: Topic :: Software Development :: Libraries
Classifier: Topic :: Software Development :: Libraries :: Python Modules
Classifier: Topic :: Utilities
Classifier: Typing :: Typed
Requires-Python: >=3.6.0
License-File: LICENSE
